legosec/__init__.py
legosec/encrypted_socket.py
legosec/identity_manager.py
legosec/sdk.py
legosec/version.py
legosec-0.1.2.dist-info/LICENSE
legosec-0.1.2.dist-info/METADATA
legosec-0.1.2.dist-info/WHEEL
legosec-0.1.2.dist-info/top_level.txt
legosec-0.1.2.dist-info/RECORD
